{
  "id": "4009222",
  "name": "白色",
  "font_family": "iconfont",
  "css_prefix_text": "icon-",
  "description": "",
  "glyphs": [
    {
      "icon_id": "34900752",
      "name": "arrow-down-rectangle",
      "font_class": "arrow-down-rectangle",
      "unicode": "e64a",
      "unicode_decimal": 58954
    },
    {
      "icon_id": "34900755",
      "name": "arrow-left-rectangle",
      "font_class": "arrow-left-rectangle",
      "unicode": "e64b",
      "unicode_decimal": 58955
    },
    {
      "icon_id": "34900763",
      "name": "arrow-right-rectangle",
      "font_class": "arrow-right-rectangle",
      "unicode": "e64e",
      "unicode_decimal": 58958
    },
    {
      "icon_id": "34900775",
      "name": "arrow-up-rectangle",
      "font_class": "arrow-up-rectangle",
      "unicode": "e655",
      "unicode_decimal": 58965
    },
    {
      "icon_id": "34900814",
      "name": "reload-rectangle",
      "font_class": "reload-rectangle",
      "unicode": "e669",
      "unicode_decimal": 58985
    },
    {
      "icon_id": "2943280",
      "name": "天气-大雨",
      "font_class": "dayu",
      "unicode": "e6e9",
      "unicode_decimal": 59113
    },
    {
      "icon_id": "2943281",
      "name": "天气-大暴雨",
      "font_class": "dabaoyu",
      "unicode": "e6ea",
      "unicode_decimal": 59114
    },
    {
      "icon_id": "2943292",
      "name": "天气-雨",
      "font_class": "yu",
      "unicode": "e6ed",
      "unicode_decimal": 59117
    },
    {
      "icon_id": "2943305",
      "name": "天气-小雨转中雨",
      "font_class": "xiaoyuzhuanzhongyu",
      "unicode": "e6f3",
      "unicode_decimal": 59123
    },
    {
      "icon_id": "27188563",
      "name": "gps",
      "font_class": "gps",
      "unicode": "e625",
      "unicode_decimal": 58917
    },
    {
      "icon_id": "2943312",
      "name": "天气-中雨转大雨",
      "font_class": "zhongyuzhuandayu",
      "unicode": "e6f6",
      "unicode_decimal": 59126
    },
    {
      "icon_id": "19990401",
      "name": "二氧化碳",
      "font_class": "eryanghuatan",
      "unicode": "e7e6",
      "unicode_decimal": 59366
    },
    {
      "icon_id": "1304875",
      "name": "减",
      "font_class": "jian",
      "unicode": "e620",
      "unicode_decimal": 58912
    },
    {
      "icon_id": "1304882",
      "name": "开关",
      "font_class": "kaiguan-open",
      "unicode": "e621",
      "unicode_decimal": 58913
    },
    {
      "icon_id": "1304889",
      "name": "添加",
      "font_class": "tianjia",
      "unicode": "e622",
      "unicode_decimal": 58914
    },
    {
      "icon_id": "35004677",
      "name": "开关-copy",
      "font_class": "kaiguan-close",
      "unicode": "e88d",
      "unicode_decimal": 59533
    },
    {
      "icon_id": "21161146",
      "name": "光照度传感器",
      "font_class": "ss-lux",
      "unicode": "e88c",
      "unicode_decimal": 59532
    },
    {
      "icon_id": "21151846",
      "name": "智能灯镜控制器",
      "font_class": "lt-mir",
      "unicode": "e883",
      "unicode_decimal": 59523
    },
    {
      "icon_id": "21161142",
      "name": "光温湿度传感器",
      "font_class": "ss-ith",
      "unicode": "e888",
      "unicode_decimal": 59528
    },
    {
      "icon_id": "21161143",
      "name": "多功能传感器",
      "font_class": "ss-los",
      "unicode": "e889",
      "unicode_decimal": 59529
    },
    {
      "icon_id": "21161151",
      "name": "溢水传感器",
      "font_class": "ss-wat",
      "unicode": "e88a",
      "unicode_decimal": 59530
    },
    {
      "icon_id": "21161152",
      "name": "温湿度传感器",
      "font_class": "ss-ths",
      "unicode": "e88b",
      "unicode_decimal": 59531
    },
    {
      "icon_id": "35005113",
      "name": "智能灯镜控制器-copy",
      "font_class": "lt-mir-copy",
      "unicode": "e88e",
      "unicode_decimal": 59534
    }
  ]
}
